voltorb_flip/__init__.py
voltorb_flip/__main__.py
voltorb_flip/console.py
voltorb_flip/game.py
voltorb_flip/levels.py
voltorb_flip-1.1.0.dist-info/entry_points.txt
voltorb_flip-1.1.0.dist-info/WHEEL
voltorb_flip-1.1.0.dist-info/METADATA
voltorb_flip-1.1.0.dist-info/RECORD
