Metadata-Version: 2.1
Name: voltorb-flip
Version: 1.1.0
Summary: A minigame of the Goldenrod and Celadon Game Corners in the Korean and Western releases of Pokémon HeartGold and SoulSilver.
Home-page: https://github.com/fferegrino/voltorb-flip
License: MIT
Author: Antonio Feregrino
Author-email: antonio.feregrino@gmail.com
Requires-Python: >=3.8,<4.0
Classifier: License :: OSI Approved :: MIT License
Classifier: Programming Language :: Python :: 3
Classifier: Programming Language :: Python :: 3.10
Classifier: Programming Language :: Python :: 3.8
Classifier: Programming Language :: Python :: 3.9
Requires-Dist: click (>=8.0.4,<9.0.0)
Requires-Dist: rich (>=11.2.0,<12.0.0)
Project-URL: Repository, https://github.com/fferegrino/voltorb-flip
